adpthr_py.cp311-win_amd64.pyd
adpthr-1.0.1.dist-info/METADATA
adpthr-1.0.1.dist-info/WHEEL
adpthr-1.0.1.dist-info/top_level.txt
adpthr-1.0.1.dist-info/RECORD
