Metadata-Version: 2.1
Name: adpthr
Version: 1.0.1
Summary: Python package for local adaptive thresholding
